kdb/data.py
kdb/version.py
kdb/main.py
kdb/events.py
kdb/plugin.py
kdb/core.py
kdb/unrepr.py
kdb/utils.py
kdb/default_config.py
kdb/config.py
kdb/__init__.py
kdb/reprconf.py
kdb/bot.py
kdb/plugins/help.py
kdb/plugins/eval.py
kdb/plugins/drone.py
kdb/plugins/autoid.py
kdb/plugins/rss.py
kdb/plugins/timers.py
kdb/plugins/dnstools.py
kdb/plugins/core.py
kdb/plugins/hello.py
kdb/plugins/rplugins.py
kdb/plugins/ctcp.py
kdb/plugins/google.py
kdb/plugins/weather.py
kdb/plugins/broadcast.py
kdb/plugins/greeting.py
kdb/plugins/irc.py
kdb/plugins/jsonrpc.py
kdb/plugins/stats.py
kdb/plugins/swatch.py
kdb/plugins/rmessage.py
kdb/plugins/__init__.py
kdb/plugins/channels.py
kdb/plugins/xmlrpc.py
kdb/plugins/spell.py
kdb/plugins/web/__init__.pyc
kdb/plugins/web/__init__.py
kdb/plugins/web/templates/index.html
kdb/plugins/web/templates/base.html
kdb/plugins/web/static/css/jquery.terminal.css
kdb/plugins/web/static/js/jquery.terminal-min.js
kdb/plugins/web/static/js/jquery-1.7.1.min.js
kdb/plugins/web/static/js/main.js
kdb/plugins/web/static/js/jquery.mousewheel-min.js
fabfile/help.py
fabfile/utils.py
fabfile/__init__.py
fabfile/docs.py
rplugins/9013e13aeccd3b43166a179539343ee59d8ce791.py
rplugins/__init__.py
kdb-1.0.2.data/scripts/kdb-message
kdb-1.0.2.dist-info/RECORD
kdb-1.0.2.dist-info/WHEEL
kdb-1.0.2.dist-info/dependency_links.txt
kdb-1.0.2.dist-info/metadata.json
kdb-1.0.2.dist-info/entry_points.txt
kdb-1.0.2.dist-info/top_level.txt
kdb-1.0.2.dist-info/DESCRIPTION.rst
kdb-1.0.2.dist-info/METADATA
