Metadata-Version: 2.0
Name: kdb
Version: 1.0.2
Summary: Knowledge (IRC) Database Bot
Home-page: http://bitbucket.org/prologic/kdb/
Author: James Mills
Author-email: James Mills, prologic at shortcircuit dot net dot au
License: MIT
Download-URL: http://bitbucket.org/prologic/kdb/downloads/
Keywords: Knowledge Database IRC Bot Framework
Platform: POSIX
Classifier: Development Status :: 5 - Production/Stable
Classifier: Environment :: No Input/Output (Daemon)
Classifier: Intended Audience :: Developers
Classifier: Intended Audience :: End Users/Desktop
Classifier: License :: OSI Approved :: GNU General Public License (GPL)
Classifier: Natural Language :: English
Classifier: Operating System :: OS Independent
Classifier: Programming Language :: Python
Classifier: Topic :: Communications :: Chat :: Internet Relay Chat
Classifier: Topic :: Scientific/Engineering :: Artificial Intelligence
Requires-Dist: Mako (==0.9.1)
Requires-Dist: funcy (==0.10)
Requires-Dist: cidict (==0.1.1)
Requires-Dist: procname (==0.3)
Requires-Dist: pymetar (==0.19)
Requires-Dist: pymills (==3.4.0)
Requires-Dist: requests (==2.2.1)
Requires-Dist: attrdict (==0.2.1)
Requires-Dist: simpleeval (==0.8)
Requires-Dist: pyenchant (==1.6.5)
Requires-Dist: feedparser (==5.1.3)
Requires-Dist: html2text (==2014.4.5)
Requires-Dist: circuits (==3.0.0.dev)
